[
  {
    "description": "",
    "elements": [
      {
        "description": "",
        "id": "generate-accessibility-report-across-our-website;generate-an-accessibility-report-for-the-playground-page",
        "keyword": "Scenario",
        "line": 32,
        "name": "Generate an accessibility report for the playground page",
        "steps": [
          {
            "keyword": "Before",
            "hidden": true,
            "result": {
              "status": "passed",
              "duration": 878297299
            }
          },
          {
            "arguments": [],
            "keyword": "Given ",
            "line": 33,
            "name": "I am on the \"home\" page",
            "match": {
              "location": "src\\step-definitions\\navigation.ts:12"
            },
            "result": {
              "status": "passed",
              "duration": 736079799
            }
          },
          {
            "arguments": [],
            "keyword": "And ",
            "line": 34,
            "name": "I click the \"playground\" button",
            "match": {
              "location": "src\\step-definitions\\click.ts:19"
            },
            "result": {
              "status": "passed",
              "duration": 684501299
            }
          },
          {
            "arguments": [],
            "keyword": "And ",
            "line": 35,
            "name": "I am directed to the \"playground\" page",
            "match": {
              "location": "src\\step-definitions\\navigation.ts:27"
            },
            "result": {
              "status": "passed",
              "duration": 16614199
            }
          },
          {
            "arguments": [],
            "keyword": "Then ",
            "line": 36,
            "name": "I generate an accessibility analysis report",
            "match": {
              "location": "src\\step-definitions\\accessibility.ts:10"
            },
            "result": {
              "status": "passed",
              "duration": 1973186299
            }
          },
          {
            "keyword": "After",
            "hidden": true,
            "result": {
              "status": "passed",
              "duration": 38127700
            }
          }
        ],
        "tags": [
          {
            "name": "@dev",
            "line": 29
          },
          {
            "name": "@accessibility",
            "line": 30
          },
          {
            "name": "@regression",
            "line": 31
          }
        ],
        "type": "scenario"
      }
    ],
    "id": "generate-accessibility-report-across-our-website",
    "line": 1,
    "keyword": "Feature",
    "name": "Generate accessibility report across our website",
    "tags": [],
    "uri": "src\\features\\accessibility\\accessibility.feature"
  }
]